LICENSE
README.md
pyproject.toml
Device_SMI.egg-info/PKG-INFO
Device_SMI.egg-info/SOURCES.txt
Device_SMI.egg-info/dependency_links.txt
Device_SMI.egg-info/top_level.txt
device_smi/__init__.py
device_smi/amd.py
device_smi/apple.py
device_smi/base.py
device_smi/cpu.py
device_smi/device.py
device_smi/intel.py
device_smi/nvidia.py
device_smi/os.py
tests/test_close.py
tests/test_cpu.py
tests/test_gpu.py
tests/test_os.py