Metadata-Version: 2.4
Name: Device-SMI
Version: 0.5.3
Summary: Retrieve gpu, cpu, and npu device info and properties from Linux/MacOS with zero package dependency.
Author-email: ModelCloud <qubitium@modelcloud.ai>
License-Expression: Apache-2.0
Project-URL: Homepage, https://github.com/ModelCloud/Device-SMI/
Keywords: hardware,monitoring,system-information,gpu,cpu,npu,metrics,device
Classifier: Programming Language :: Python :: 3
Classifier: Operating System :: OS Independent
Requires-Python: >=3
License-File: LICENSE
Dynamic: license-file
